PyEasyDB/__init__.py
PyEasyDB/core.py
pyeasydb-0.1.1.dist-info/licenses/LICENSE
pyeasydb-0.1.1.dist-info/METADATA
pyeasydb-0.1.1.dist-info/WHEEL
pyeasydb-0.1.1.dist-info/top_level.txt
pyeasydb-0.1.1.dist-info/RECORD
