Metadata-Version: 2.4
Name: PyEasyDB
Version: 0.1.1
Summary: A simple and lightweight Python library for easy database management.
Author: RedSnows
Author-email: id.suzuya@email.com
Classifier: Programming Language :: Python :: 3
Classifier: License :: OSI Approved :: MIT License
Classifier: Operating System :: OS Independent
Requires-Python: >=3.6
License-File: LICENSE
Dynamic: author
Dynamic: author-email
Dynamic: classifier
Dynamic: description
Dynamic: description-content-type
Dynamic: license-file
Dynamic: requires-python
Dynamic: summary
